pypeertalk/__init__.py
pypeertalk/core/pypeertalk_core.cpython-310-x86_64-linux-gnu.so
pypeertalk/core/pypeertalk_core.cpython-311-x86_64-linux-gnu.so
pypeertalk/core/pypeertalk_core.cpython-312-x86_64-linux-gnu.so
pypeertalk/core/pypeertalk_core.cpython-313-x86_64-linux-gnu.so
pypeertalk/core/pypeertalk_core.cpython-38-x86_64-linux-gnu.so
pypeertalk/core/pypeertalk_core.cpython-39-x86_64-linux-gnu.so
pypeertalk/core/pypeertalk_core.pyi
pypeertalk/core/include/peertalk_client.h
pypeertalk/core/src/peertalk_client.cpp
pypeertalk/core/src/peertalk_pybind.cpp
pypeertalk-0.1.1.dist-info/METADATA
pypeertalk-0.1.1.dist-info/WHEEL
pypeertalk-0.1.1.dist-info/top_level.txt
pypeertalk-0.1.1.dist-info/RECORD
