Metadata-Version: 2.4
Name: pypeertalk
Version: 0.1.1
Summary: Python binding for PeerTalk client through USB
Author-email: Yihuai Gao <yihuai@stanford.edu>
Project-URL: Homepage, https://github.com/yihuai-gao/pypeertalk
Classifier: Programming Language :: Python :: 3
Classifier: License :: OSI Approved :: MIT License
Classifier: Operating System :: OS Independent
